libclamav_py/__init__.py
libclamav_py/clamav.py
libclamav_py/config/__init__.py
libclamav_py/config/base.py
libclamav_py/config/database.py
libclamav_py/config/engine.py
libclamav_py/config/scan.py
libclamav_py/utils/__init__.py
libclamav_py/utils/constant.py
libclamav_py-0.2.0.dist-info/LICENSE
libclamav_py-0.2.0.dist-info/METADATA
libclamav_py-0.2.0.dist-info/WHEEL
libclamav_py-0.2.0.dist-info/RECORD
