Metadata-Version: 2.1
Name: libclamav-py
Version: 0.2.0
Summary: libclamav-py is a Python library that provides a seamless interface to the ClamAV antivirus engine via libClamAV. This wrapper directly calls the C API of Libclamav
Home-page: https://github.com/tkasuz/libclamav-py
Author: tkasuz
Author-email: 63289889+tkasuz@users.noreply.github.com
Requires-Python: >=3.12,<4.0
Classifier: Programming Language :: Python :: 3
Classifier: Programming Language :: Python :: 3.12
Classifier: Programming Language :: Python :: 3.13
Requires-Dist: pydantic (>=2.10.3,<3.0.0)
Project-URL: Repository, https://github.com/tkasuz/libclamav-py
